capguard/__init__.py
capguard/decorators.py
capguard/classifiers/__init__.py
capguard/classifiers/llm_based.py
capguard/classifiers/rule_based.py
capguard/core/__init__.py
capguard/core/classifier.py
capguard/core/enforcer.py
capguard/core/exceptions.py
capguard/core/registry.py
capguard/integrations/__init__.py
capguard/integrations/langchain.py
capguard/models/__init__.py
capguard/models/audit_log.py
capguard/models/capability_token.py
capguard/models/tool_definition.py
capguard/prompts/__init__.py
capguard/prompts/classification.py
capguard-0.1.6.dist-info/licenses/LICENSE
capguard-0.1.6.dist-info/METADATA
capguard-0.1.6.dist-info/WHEEL
capguard-0.1.6.dist-info/top_level.txt
capguard-0.1.6.dist-info/RECORD
