Metadata-Version: 2.4
Name: capguard
Version: 0.1.6
Summary: Capability-based security for LLM agents
Author-email: CapGuard Team <83171543+Nixbu@users.noreply.github.com>
License: Apache-2.0
Project-URL: Homepage, https://github.com/capguard/capguard
Project-URL: Documentation, https://capguard.com/docs
Project-URL: Repository, https://github.com/capguard/capguard
Project-URL: Bug Tracker, https://github.com/capguard/capguard/issues
Keywords: llm,security,ai,prompt-injection,agents,capability
Classifier: Development Status :: 3 - Alpha
Classifier: Intended Audience :: Developers
Classifier: Topic :: Security
Classifier: Topic :: Scientific/Engineering :: Artificial Intelligence
Classifier: License :: OSI Approved :: Apache Software License
Classifier: Programming Language :: Python :: 3
Classifier: Programming Language :: Python :: 3.9
Classifier: Programming Language :: Python :: 3.10
Classifier: Programming Language :: Python :: 3.11
Classifier: Programming Language :: Python :: 3.12
Requires-Python: >=3.9
License-File: LICENSE
Requires-Dist: pydantic>=2.0.0
Provides-Extra: dev
Requires-Dist: pytest>=7.0; extra == "dev"
Requires-Dist: pytest-asyncio>=0.21.0; extra == "dev"
Requires-Dist: black>=23.0; extra == "dev"
Requires-Dist: ruff>=0.1.0; extra == "dev"
Requires-Dist: mypy>=1.0; extra == "dev"
Provides-Extra: llm
Requires-Dist: openai>=1.0.0; extra == "llm"
Provides-Extra: langchain
Requires-Dist: langchain>=0.1.0; extra == "langchain"
Requires-Dist: langchain-openai>=0.0.5; extra == "langchain"
Requires-Dist: langchain-community>=0.0.20; extra == "langchain"
Dynamic: license-file
